CHANGES
COPYING.LGPLv3
LICENSE
MANIFEST.in
README
ez_setup.py
requirements.txt
setup.py
dbresolver/__init__.py
dbresolver/admin.py
dbresolver/forms.py
dbresolver/models.py
django_dburlresolvers.egg-info/PKG-INFO
django_dburlresolvers.egg-info/SOURCES.txt
django_dburlresolvers.egg-info/dependency_links.txt
django_dburlresolvers.egg-info/requires.txt
django_dburlresolvers.egg-info/top_level.txt